xaal/__init__.py
xaal/dummy/__init__.py
xaal/dummy/__main__.py
xaal/dummy/asyncbot.py
xaal/dummy/autobot.py
xaal/dummy/lamp.py
xaal/dummy/lamp_minimal.py
xaal/dummy/power_relay.py
xaal/dummy/temperature.py
xaal_dummy-0.3.2.dist-info/METADATA
xaal_dummy-0.3.2.dist-info/WHEEL
xaal_dummy-0.3.2.dist-info/top_level.txt
xaal_dummy-0.3.2.dist-info/RECORD
